{
  "version": "7",
  "dialect": "postgresql",
  "entries": [
    {
      "idx": 0,
      "version": "7",
      "when": 1738153110616,
      "tag": "0000_outstanding_lady_bullseye",
      "breakpoints": true
    },
    {
      "idx": 1,
      "version": "7",
      "when": 1738230694513,
      "tag": "0001_cultured_doctor_faustus",
      "breakpoints": true
    },
    {
      "idx": 2,
      "version": "7",
      "when": 1738260801380,
      "tag": "0002_flawless_snowbird",
      "breakpoints": true
    },
    {
      "idx": 3,
      "version": "7",
      "when": 1738315578705,
      "tag": "0003_nasty_wasp",
      "breakpoints": true
    },
    {
      "idx": 4,
      "version": "7",
      "when": 1738321914274,
      "tag": "0004_breezy_forge",
      "breakpoints": true
    },
    {
      "idx": 5,
      "version": "7",
      "when": 1738597999988,
      "tag": "0005_icy_matthew_murdock",
      "breakpoints": true
    },
    {
      "idx": 6,
      "version": "7",
      "when": 1738664222667,
      "tag": "0006_clumsy_marten_broadcloak",
      "breakpoints": true
    },
    {
      "idx": 7,
      "version": "7",
      "when": 1738675891792,
      "tag": "0007_noisy_chronomancer",
      "breakpoints": true
    },
    {
      "idx": 8,
      "version": "7",
      "when": 1739208550578,
      "tag": "0008_cute_kinsey_walden",
      "breakpoints": true
    },
    {
      "idx": 9,
      "version": "7",
      "when": 1739465795619,
      "tag": "0009_broken_flatman",
      "breakpoints": true
    },
    {
      "idx": 10,
      "version": "7",
      "when": 1739474374789,
      "tag": "0010_chemical_the_spike",
      "breakpoints": true
    },
    {
      "idx": 11,
      "version": "7",
      "when": 1739544210987,
      "tag": "0011_fantastic_stature",
      "breakpoints": true
    },
    {
      "idx": 12,
      "version": "7",
      "when": 1739972610132,
      "tag": "0012_new_dark_beast",
      "breakpoints": true
    },
    {
      "idx": 13,
      "version": "7",
      "when": 1741621798126,
      "tag": "0013_pale_talisman",
      "breakpoints": true
    }
  ]
}